multicaller/__init__.py
multicaller/multicaller.py
multicaller/abi/multicall3.json
multicaller-0.0.0a16.dist-info/METADATA
multicaller-0.0.0a16.dist-info/WHEEL
multicaller-0.0.0a16.dist-info/top_level.txt
multicaller-0.0.0a16.dist-info/RECORD
