Metadata-Version: 2.1
Name: multicaller
Version: 0.0.0a16
Summary: web3py multicaller simplified interface
Home-page: https://github.com/gerrrg/multicaller
Author: gerrrg
Author-email: gerrrrrrrg@gmail.com
Project-URL: Bug Tracker, https://github.com/gerrrg/multicaller/issues
Classifier: Intended Audience :: Developers
Classifier: Programming Language :: Python :: 3
Classifier: License :: OSI Approved :: GNU General Public License v3 (GPLv3)
Classifier: Operating System :: OS Independent
Requires-Dist: web3 (==5.19.0)
